{
  "Settings": {
    "Title": "Settings",
    "Description": "Manage the configuration for project auditing.",
    "NuGetAuditConfig": "NuGet Audit Configuration",
    "AuditMode": "Audit Mode",
    "AuditModeDescription": "Direct: Check only direct package references. All: Check direct and all transitive package references.",
    "AuditLevel": "Audit Level (Severity)",
    "AuditLevelDescription": "Defines the severity level from which vulnerabilities are reported.",
    "SaveButton": "Save Settings",
    "SuccessMessage": "Successfully saved!",
    "LoadingSettings": "Loading Settings...",
    "Language": "Language",
    "LanguageDescription": "Choose the language for the user interface."
  },
  "Index": {
    "Title": "Project Auditor",
    "Description": "Scan and update NuGet packages in your .NET projects.",
    "ProjectDirectoryLabel": "Project Directory",
    "OpenExplorer": "Open in Explorer",
    "ScanProject": "Scan Project",
    "Scanning": "Scanning...",
    "Placeholder": "C:\\Path\\to\\Solution",
    "StartAutoFix": "Start Auto-Fix",
    "FixRunning": "Running fixes...",
    "NoPackagesFound": "No updates found.",
    "NoUpdatesMessage": "Your project is up to date!",
    "FoundPackages": "Found Packages",
    "ApplyUpdatesButton": "Apply Updates",
    "ApplyingUpdates": "Applying updates...",
    "FixedSuccessfully": "Successfully updated",
    "FixFailed": "Update failed",
    "LogGenerated": "Log {logFile} was generated.",
    "SomeUpdatesFailed": "Some updates could not be verified and were rolled back.",
    "TableHeaderProject": "Project",
    "TableHeaderPackage": "Package Name",
    "TableHeaderCurrent": "Current",
    "TableHeaderStatus": "Status",
    "TableHeaderTargetVersion": "Target Version",
    "StatusOutdated": "Outdated",
    "StatusDeprecated": "Deprecated",
    "OtherPackages": "Other Packages",
    "IgnoreOption": "Ignore",
    "GroupHeader": "GROUP:"
  },
  "Progress": {
    "Scanning": "Scanning",
    "ScanningVulnerable": "Scanning Vulnerable",
    "ScanningOutdated": "Scanning Outdated",
    "ScanningDeprecated": "Scanning Deprecated",
    "FetchingVersions": "Fetching Versions",
    "ApplyingUpdates": "Applying Updates",
    "Verifying": "Verifying",
    "Completed": "Completed",
    "Failed": "Failed",
    "Package": "Package",
    "Project": "Project"
  },
  "Scanning": {
    "ScanningVulnerable": "Scanning for vulnerable packages...",
    "ScanningOutdated": "Scanning for outdated packages...",
    "ScanningDeprecated": "Scanning for deprecated packages...",
    "FetchingVersions": "Fetching versions for {packageId}... ({current}/{total})",
    "ScanCompletedSingle": "Scan completed. 1 package requires updates.",
    "ScanCompletedMulti": "Scan completed. {count} packages require updates.",
    "ErrorDuringScan": "Error during scan: {error}"
  },
  "Upgrading": {
    "StartingUpgrades": "Starting targeted upgrades...",
    "NoUpgradesSelected": "No upgrades selected to apply.",
    "ApplyingGroupUpgrade": "Applying upgrade for group '{group}' ({count} packages) ({current}/{total})",
    "GroupUpdateSuccess": "✓ Group '{group}' updated successfully.",
    "GroupUpdateFailed": "✗ Group '{group}' failed. Rolled back. {error}",
    "GroupRollbackSuccess": "Rollback successful for group '{group}'.",
    "GroupRollbackFailed": "CRITICAL: Rollback build also failed for group '{group}'. Rollback error: {error}",
    "GroupFallbackMessage": "Fallback: Applying updates for '{group}' individually...",
    "UpdatingPackage": "Updating {packageId} to {version}...",
    "VerifyingBuild": "Verifying build for {packageId}...",
    "BuildVerified": "✓ Build verified for {packageId} {version}",
    "BuildVerifyFailed": "Build failed for {packageId}. Rolling back to {version}... Error: {error}",
    "PackageRollbackSuccess": "Rollback successful for {packageId}.",
    "PackageRollbackFailed": "CRITICAL: Rollback build also failed for {packageId}. Rollback error: {error}",
    "CompletedWithFailures": "Completed with failures. {count} packages were rolled back.",
    "CompletedSuccessfully": "All upgrades completed successfully!",
    "CriticalError": "Critical error: {error}",
    "ErrorUpdatingPackage": "Error updating {packageId}: {error}"
  },
  "Errors": {
    "DirectoryNotFound": "The entered directory does not exist.",
    "OpenExplorerError": "Error opening explorer: {error}",
    "ScanError": "Error during scan: {error}",
    "FixError": "Error during fixing: {error}",
    "GroupFallbackPrompt": "The group update for '{group}' ({count} packages) failed.\nThere were probably build errors.\n\nDo you want to try a fallback and update the packages individually one by one (takes longer)?",
    "CliProcessStartFailed": "Failed to start dotnet CLI process.",
    "BuildTimeout": "Build operation timed out after 2 minutes.",
    "UnexpectedBuildError": "Unexpected error during build: {error}",
    "BuildFailedUnknown": "Build failed with unknown error.",
    "BuildFailedWithErrors": "Build failed with errors:",
    "BuildFailed": "Build failed:"
  },
  "ErrorMessages": {
    "DirectoryNotFound": "Directory not found",
    "InvalidPath": "Invalid path",
    "NoProjectFound": "No project found in this directory",
    "BuildFailed": "Build failed",
    "UpdateFailed": "Update failed"
  },
  "Audit": {
    "LogTitle": "Audit Log",
    "NoLogsFound": "No log entries found.",
    "OldVersion": "Old:",
    "NewVersion": "New:",
    "File": "File:",
    "CloseButton": "Close",
    "StatusSuccess": "Success",
    "StatusFailed": "Failed",
    "Error": "Error:"
  }
}